subprocess_vcr/__init__.py
subprocess_vcr/core.py
subprocess_vcr/filters.py
subprocess_vcr/pytest_plugin.py
subprocess_vcr-0.1.0.dist-info/licenses/LICENSE
subprocess_vcr-0.1.0.dist-info/METADATA
subprocess_vcr-0.1.0.dist-info/WHEEL
subprocess_vcr-0.1.0.dist-info/entry_points.txt
subprocess_vcr-0.1.0.dist-info/top_level.txt
subprocess_vcr-0.1.0.dist-info/RECORD
