Metadata-Version: 2.4
Name: subprocess-vcr
Version: 0.1.0
Summary: VCR for subprocess - record and replay subprocess calls for testing
Author-email: Maximilian Roos <m@maxroos.com>
License-Expression: MIT
Project-URL: Homepage, https://github.com/max-sixty/subprocess-vcr
Project-URL: Repository, https://github.com/max-sixty/subprocess-vcr
Project-URL: Issues, https://github.com/max-sixty/subprocess-vcr/issues
Keywords: testing,subprocess,vcr,mock,pytest,recording,replay
Classifier: Development Status :: 4 - Beta
Classifier: Intended Audience :: Developers
Classifier: Programming Language :: Python :: 3
Classifier: Programming Language :: Python :: 3.9
Classifier: Programming Language :: Python :: 3.10
Classifier: Programming Language :: Python :: 3.11
Classifier: Programming Language :: Python :: 3.12
Classifier: Framework :: Pytest
Classifier: Topic :: Software Development :: Testing
Classifier: Topic :: Software Development :: Testing :: Mocking
Requires-Python: >=3.9
License-File: LICENSE
Requires-Dist: pyyaml>=6.0
Provides-Extra: dev
Requires-Dist: pytest>=7.0.0; extra == "dev"
Requires-Dist: pytest-xdist>=3.5.0; extra == "dev"
Requires-Dist: mypy>=1.8.0; extra == "dev"
Requires-Dist: ruff>=0.9.7; extra == "dev"
Requires-Dist: pre-commit>=3.5.0; extra == "dev"
Requires-Dist: types-pyyaml>=6.0.12; extra == "dev"
Dynamic: license-file
